live_transcribe/__init__.py
live_transcribe/__main__.py
live_transcribe/_poc.py
live_transcribe/audio_pasimple.py
live_transcribe/qt.py
live_transcribe/text.py
live_transcribe/transcribe.py
live_transcribe-0.1.2.dist-info/entry_points.txt
live_transcribe-0.1.2.dist-info/WHEEL
live_transcribe-0.1.2.dist-info/METADATA
live_transcribe-0.1.2.dist-info/RECORD
