Metadata-Version: 2.1
Name: live-transcribe
Version: 0.1.2
Summary: Real-time audio transcription. Runs OpenAI's Whisper locally.
License: MIT
Author: Tomasz Łakota
Author-email: tomasz.lakota@gmail.com
Requires-Python: >=3.8,<4.0
Classifier: License :: OSI Approved :: MIT License
Classifier: Programming Language :: Python :: 3
Classifier: Programming Language :: Python :: 3.10
Classifier: Programming Language :: Python :: 3.8
Classifier: Programming Language :: Python :: 3.9
Requires-Dist: numpy (>=1.23,<2.0,!=1.24.0,!=1.24.1,!=1.24.2)
Requires-Dist: openai-whisper (>=20230314,<20230315)
Requires-Dist: pasimple (>=0.0.1,<0.0.2)
Requires-Dist: pulsectl (>=22.3.2,<23.0.0)
